gitflow_easyrelease/__init__.py
gitflow_easyrelease/application.py
gitflow_easyrelease/cli_file.py
gitflow_easyrelease/color_output.py
gitflow_easyrelease/is_semver.py
gitflow_easyrelease/repo_info.py
gitflow_easyrelease/semver.py
gitflow_easyrelease/subcommand.py
gitflow_easyrelease-0.3.2.dist-info/DESCRIPTION.rst
gitflow_easyrelease-0.3.2.dist-info/METADATA
gitflow_easyrelease-0.3.2.dist-info/RECORD
gitflow_easyrelease-0.3.2.dist-info/WHEEL
gitflow_easyrelease-0.3.2.dist-info/entry_points.txt
gitflow_easyrelease-0.3.2.dist-info/metadata.json
gitflow_easyrelease-0.3.2.dist-info/top_level.txt
