Metadata-Version: 2.0
Name: gitflow-easyrelease
Version: 0.3.2
Summary: Shortcuts for git flow release with semver support
Home-page: https://github.com/wizardsoftheweb/gitflow-easyrelease#readme
Author: CJ Harries
Author-email: cj@wizardsoftheweb.pro
License: ISC
Project-URL: Issue Tracker, https://github.com/wizardsoftheweb/gitflow-easyrelease/issues
Keywords: git,gitflow,gitflow-avh
Platform: UNKNOWN
Classifier: Development Status :: 3 - Alpha
Classifier: Environment :: Console
Classifier: Topic :: Software Development :: Version Control :: Git
Requires-Dist: argparse-color-formatter
Requires-Dist: ansicolors
Requires-Dist: pytest-runner
